spyobject/__init__.py
SPyObject-0.1.23.dist-info/LICENSE
SPyObject-0.1.23.dist-info/METADATA
SPyObject-0.1.23.dist-info/WHEEL
SPyObject-0.1.23.dist-info/top_level.txt
SPyObject-0.1.23.dist-info/RECORD
